yyyy_mm_dd/__init__.py
yyyy_mm_dd-0.1.2.dist-info/LICENSE
yyyy_mm_dd-0.1.2.dist-info/METADATA
yyyy_mm_dd-0.1.2.dist-info/WHEEL
yyyy_mm_dd-0.1.2.dist-info/top_level.txt
yyyy_mm_dd-0.1.2.dist-info/RECORD
